{
  "generatedAt": "2026-07-22T01:13:13Z",
  "teams": [
    {
      "attack": 1.1999992139017823,
      "defense": 1.2275844377197676,
      "elo": 2053.4471620876725,
      "id": "argentina",
      "name": "Argentina",
      "overall": 2.42758365162155,
      "style": {}
    },
    {
      "attack": 0.8188927730228414,
      "defense": 1.3087074882916343,
      "elo": 1876.7926598295635,
      "id": "morocco",
      "name": "Morocco",
      "overall": 2.1276002613144755,
      "style": {}
    },
    {
      "attack": 1.1775223426651316,
      "defense": 0.9460122968246991,
      "elo": 1896.7476671408413,
      "id": "japan",
      "name": "Japan",
      "overall": 2.1235346394898307,
      "style": {}
    },
    {
      "attack": 1.2187755627474093,
      "defense": 0.8473925193182855,
      "elo": 1980.0512024449094,
      "id": "brazil",
      "name": "Brazil",
      "overall": 2.066168082065695,
      "style": {}
    },
    {
      "attack": 1.2821098208527346,
      "defense": 0.7564579009151078,
      "elo": 1948.9658779453314,
      "id": "colombia",
      "name": "Colombia",
      "overall": 2.0385677217678424,
      "style": {}
    },
    {
      "attack": 1.1487411202090219,
      "defense": 0.8247433215608561,
      "elo": 2025.3672625660333,
      "id": "spain",
      "name": "Spain",
      "overall": 1.973484441769878,
      "style": {}
    },
    {
      "attack": 0.9507236393792359,
      "defense": 0.9692469856344819,
      "elo": 1797.7388122110344,
      "id": "australia",
      "name": "Australia",
      "overall": 1.9199706250137178,
      "style": {}
    },
    {
      "attack": 0.8479926220909682,
      "defense": 1.017343454271334,
      "elo": 1865.9549728160414,
      "id": "mexico",
      "name": "Mexico",
      "overall": 1.8653360763623021,
      "style": {}
    },
    {
      "attack": 0.9595145452120297,
      "defense": 0.8456605840229073,
      "elo": 1944.9958550695392,
      "id": "england",
      "name": "England",
      "overall": 1.8051751292349372,
      "style": {}
    },
    {
      "attack": 1.0020519834859907,
      "defense": 0.7761509516679427,
      "elo": 1983.976667597176,
      "id": "france",
      "name": "France",
      "overall": 1.7782029351539332,
      "style": {}
    },
    {
      "attack": 1.2026873990387041,
      "defense": 0.5669565233025389,
      "elo": 1921.678269096701,
      "id": "germany",
      "name": "Germany",
      "overall": 1.769643922341243,
      "style": {}
    },
    {
      "attack": 0.512669105825608,
      "defense": 1.2348621238443178,
      "elo": 1856.494651268428,
      "id": "ecuador",
      "name": "Ecuador",
      "overall": 1.7475312296699257,
      "style": {}
    },
    {
      "attack": 1.0627601157481257,
      "defense": 0.6170623470407118,
      "elo": 1911.9436023559144,
      "id": "netherlands",
      "name": "Netherlands",
      "overall": 1.6798224627888376,
      "style": {}
    },
    {
      "attack": 1.0246885234189314,
      "defense": 0.5845064258503622,
      "elo": 1937.5872959946169,
      "id": "portugal",
      "name": "Portugal",
      "overall": 1.6091949492692934,
      "style": {}
    },
    {
      "attack": 0.8876198569548608,
      "defense": 0.6890580584506396,
      "elo": 1794.7211190210182,
      "id": "canada",
      "name": "Canada",
      "overall": 1.5766779154055004,
      "style": {}
    },
    {
      "attack": 0.6999670725592525,
      "defense": 0.8688117332128473,
      "elo": 1861.3938794016053,
      "id": "uruguay",
      "name": "Uruguay",
      "overall": 1.5687788057720997,
      "style": {}
    },
    {
      "attack": 1.0766198708114543,
      "defense": 0.47257997600634755,
      "elo": 1812.303611499801,
      "id": "norway",
      "name": "Norway",
      "overall": 1.5491998468178019,
      "style": {}
    },
    {
      "attack": 0.9217866494973893,
      "defense": 0.6060883912542382,
      "elo": 1835.9668477721048,
      "id": "switzerland",
      "name": "Switzerland",
      "overall": 1.5278750407516275,
      "style": {}
    },
    {
      "attack": 0.901142391930349,
      "defense": 0.612840618035316,
      "elo": 1786.9809241898092,
      "id": "united-states",
      "name": "United States",
      "overall": 1.5139830099656648,
      "style": {}
    },
    {
      "attack": 0.8816986231656672,
      "defense": 0.601442720989174,
      "elo": 1803.2880704338431,
      "id": "south-korea",
      "name": "South Korea",
      "overall": 1.4831413441548411,
      "style": {}
    },
    {
      "attack": 0.6851271617044117,
      "defense": 0.7910444294468391,
      "elo": 1775.023258325969,
      "id": "paraguay",
      "name": "Paraguay",
      "overall": 1.4761715911512507,
      "style": {}
    },
    {
      "attack": 0.8623615771634704,
      "defense": 0.5696002389600426,
      "elo": 1827.865449299952,
      "id": "iran",
      "name": "Iran",
      "overall": 1.431961816123513,
      "style": {}
    },
    {
      "attack": 0.8269054437784084,
      "defense": 0.5864862288602481,
      "elo": 1777.2447729029116,
      "id": "russia",
      "name": "Russia",
      "overall": 1.4133916726386566,
      "style": {}
    },
    {
      "attack": 0.7902313834255459,
      "defense": 0.6137643673621364,
      "elo": 1546.92146543099,
      "id": "tamil-eelam",
      "name": "Tamil Eelam",
      "overall": 1.4039957507876824,
      "style": {}
    },
    {
      "attack": 0.8547170308174552,
      "defense": 0.5246199251352803,
      "elo": 1838.6271249635104,
      "id": "denmark",
      "name": "Denmark",
      "overall": 1.3793369559527355,
      "style": {}
    },
    {
      "attack": 1.302278380872488,
      "defense": 0.045357277037488174,
      "elo": 1659.634390695122,
      "id": "isle-of-man",
      "name": "Isle of Man",
      "overall": 1.3476356579099762,
      "style": {}
    },
    {
      "attack": 0.7932962630348509,
      "defense": 0.5136673999923588,
      "elo": 1808.2632589784655,
      "id": "senegal",
      "name": "Senegal",
      "overall": 1.3069636630272097,
      "style": {}
    },
    {
      "attack": 0.74296092170097,
      "defense": 0.5602731257000794,
      "elo": 1747.2861637747812,
      "id": "nigeria",
      "name": "Nigeria",
      "overall": 1.3032340474010493,
      "style": {}
    },
    {
      "attack": 0.8084538730517489,
      "defense": 0.48354164355527396,
      "elo": 1662.038362273281,
      "id": "new-zealand",
      "name": "New Zealand",
      "overall": 1.291995516607023,
      "style": {}
    },
    {
      "attack": 0.8469783260607513,
      "defense": 0.431854748894019,
      "elo": 1890.2262406185996,
      "id": "belgium",
      "name": "Belgium",
      "overall": 1.2788330749547703,
      "style": {}
    },
    {
      "attack": 0.7886626713455807,
      "defense": 0.47570152287140277,
      "elo": 1819.2717817110117,
      "id": "algeria",
      "name": "Algeria",
      "overall": 1.2643641942169834,
      "style": {}
    },
    {
      "attack": 0.5655374733207789,
      "defense": 0.6871832035385216,
      "elo": 1723.3053985679987,
      "id": "uzbekistan",
      "name": "Uzbekistan",
      "overall": 1.2527206768593004,
      "style": {}
    },
    {
      "attack": 0.6856808748680129,
      "defense": 0.5566622881047326,
      "elo": 1722.5335908236698,
      "id": "scotland",
      "name": "Scotland",
      "overall": 1.2423431629727455,
      "style": {}
    },
    {
      "attack": 0.7516762481717985,
      "defense": 0.46672782014523856,
      "elo": 1874.4157714903065,
      "id": "italy",
      "name": "Italy",
      "overall": 1.218404068317037,
      "style": {}
    },
    {
      "attack": 0.466857074427937,
      "defense": 0.7172824469620052,
      "elo": 1762.1888129749448,
      "id": "ivory-coast",
      "name": "Ivory Coast",
      "overall": 1.1841395213899422,
      "style": {}
    },
    {
      "attack": 0.6768443072643423,
      "defense": 0.4837386357910687,
      "elo": 1811.5670541583422,
      "id": "austria",
      "name": "Austria",
      "overall": 1.1605829430554109,
      "style": {}
    },
    {
      "attack": 0.7101890255539572,
      "defense": 0.44295878710051234,
      "elo": 1734.7616990321978,
      "id": "venezuela",
      "name": "Venezuela",
      "overall": 1.1531478126544696,
      "style": {}
    },
    {
      "attack": 0.6966718533902182,
      "defense": 0.44714291786621185,
      "elo": 1862.6862970213135,
      "id": "croatia",
      "name": "Croatia",
      "overall": 1.1438147712564302,
      "style": {}
    },
    {
      "attack": 0.34077415682881484,
      "defense": 0.7970413650065465,
      "elo": 1662.8752642268994,
      "id": "dr-congo",
      "name": "DR Congo",
      "overall": 1.1378155218353614,
      "style": {}
    },
    {
      "attack": 0.5464065682276732,
      "defense": 0.5562471005002019,
      "elo": 1649.7044278705796,
      "id": "saudi-arabia",
      "name": "Saudi Arabia",
      "overall": 1.102653668727875,
      "style": {}
    },
    {
      "attack": 0.6944906248370402,
      "defense": 0.3947803145812902,
      "elo": 1717.1912891635363,
      "id": "panama",
      "name": "Panama",
      "overall": 1.0892709394183304,
      "style": {}
    },
    {
      "attack": 0.6598201261687631,
      "defense": 0.4146759832175769,
      "elo": 1715.3041406013965,
      "id": "greece",
      "name": "Greece",
      "overall": 1.0744961093863399,
      "style": {}
    },
    {
      "attack": 0.7413234122167042,
      "defense": 0.3242363784097089,
      "elo": 1795.9190304763251,
      "id": "turkey",
      "name": "Turkey",
      "overall": 1.0655597906264132,
      "style": {}
    },
    {
      "attack": 0.7674929666687723,
      "defense": 0.27850396586459436,
      "elo": 1667.1654892099036,
      "id": "jordan",
      "name": "Jordan",
      "overall": 1.0459969325333667,
      "style": {}
    },
    {
      "attack": 0.6174819395711454,
      "defense": 0.41489731318416495,
      "elo": 1745.5613305609686,
      "id": "chile",
      "name": "Chile",
      "overall": 1.0323792527553104,
      "style": {}
    },
    {
      "attack": 1.0616408990464836,
      "defense": -0.03301226826315077,
      "elo": 1753.077612204527,
      "id": "jersey",
      "name": "Jersey",
      "overall": 1.0286286307833328,
      "style": {}
    },
    {
      "attack": 0.31972407607204206,
      "defense": 0.6956381512966561,
      "elo": 1663.6362175212619,
      "id": "mali",
      "name": "Mali",
      "overall": 1.0153622273686982,
      "style": {}
    },
    {
      "attack": 0.49773835721299464,
      "defense": 0.48552316339764506,
      "elo": 1679.7183171939337,
      "id": "iraq",
      "name": "Iraq",
      "overall": 0.9832615206106396,
      "style": {}
    },
    {
      "attack": 0.3687968733170916,
      "defense": 0.6026780027932529,
      "elo": 1749.8689838911032,
      "id": "egypt",
      "name": "Egypt",
      "overall": 0.9714748761103444,
      "style": {}
    },
    {
      "attack": 0.44656132425061873,
      "defense": 0.5071434585952597,
      "elo": 1615.0804941959418,
      "id": "ynys-m\u00f4n",
      "name": "Ynys M\u00f4n",
      "overall": 0.9537047828458785,
      "style": {}
    },
    {
      "attack": 0.5882935389288965,
      "defense": 0.32614151572250566,
      "elo": 1671.2678212340213,
      "id": "costa-rica",
      "name": "Costa Rica",
      "overall": 0.9144350546514022,
      "style": {}
    },
    {
      "attack": 0.6746073900106841,
      "defense": 0.21438168211641867,
      "elo": 1625.9386035499722,
      "id": "haiti",
      "name": "Haiti",
      "overall": 0.8889890721271028,
      "style": {}
    },
    {
      "attack": 0.5314613373401869,
      "defense": 0.3388470522165769,
      "elo": 1622.9110082894233,
      "id": "united-arab-emirates",
      "name": "United Arab Emirates",
      "overall": 0.8703083895567638,
      "style": {}
    },
    {
      "attack": 0.865492796636958,
      "defense": -0.013337130767871642,
      "elo": 1734.9648086784437,
      "id": "sweden",
      "name": "Sweden",
      "overall": 0.8521556658690863,
      "style": {}
    },
    {
      "attack": 0.2989129247865681,
      "defense": 0.5424266522440803,
      "elo": 1665.6319879927412,
      "id": "cameroon",
      "name": "Cameroon",
      "overall": 0.8413395770306484,
      "style": {}
    },
    {
      "attack": 0.37523679820522854,
      "defense": 0.44388513814323627,
      "elo": 1614.4288077340818,
      "id": "ghana",
      "name": "Ghana",
      "overall": 0.8191219363484648,
      "style": {}
    },
    {
      "attack": 0.6438827678923535,
      "defense": 0.15010083258111181,
      "elo": 1778.0489640874594,
      "id": "ukraine",
      "name": "Ukraine",
      "overall": 0.7939836004734654,
      "style": {}
    },
    {
      "attack": 0.5673276200407794,
      "defense": 0.20405316171847185,
      "elo": 1731.318071625449,
      "id": "poland",
      "name": "Poland",
      "overall": 0.7713807817592513,
      "style": {}
    },
    {
      "attack": 0.43800856470619953,
      "defense": 0.313924080237775,
      "elo": 1640.504516234016,
      "id": "kosovo",
      "name": "Kosovo",
      "overall": 0.7519326449439745,
      "style": {}
    },
    {
      "attack": 0.3403571723970772,
      "defense": 0.37643351496410893,
      "elo": 1624.7502338604263,
      "id": "honduras",
      "name": "Honduras",
      "overall": 0.7167906873611861,
      "style": {}
    },
    {
      "attack": 0.3969677585501437,
      "defense": 0.2773771978812582,
      "elo": 1628.12991551901,
      "id": "south-africa",
      "name": "South Africa",
      "overall": 0.6743449564314019,
      "style": {}
    },
    {
      "attack": 0.3195019222054902,
      "defense": 0.3303991136680995,
      "elo": 1548.0348900004744,
      "id": "syria",
      "name": "Syria",
      "overall": 0.6499010358735897,
      "style": {}
    },
    {
      "attack": 0.49873831071612784,
      "defense": 0.14689961707950056,
      "elo": 1725.8029027318773,
      "id": "czechia",
      "name": "Czechia",
      "overall": 0.6456379277956283,
      "style": {}
    },
    {
      "attack": 0.2921822293468449,
      "defense": 0.33438506738837875,
      "elo": 1740.642456787966,
      "id": "serbia",
      "name": "Serbia",
      "overall": 0.6265672967352236,
      "style": {}
    },
    {
      "attack": 0.4566313463282035,
      "defense": 0.15659590649331662,
      "elo": 1640.8165839958494,
      "id": "georgia",
      "name": "Georgia",
      "overall": 0.6132272528215201,
      "style": {}
    },
    {
      "attack": 0.3621602566008146,
      "defense": 0.2462532902240793,
      "elo": 1715.1402940729731,
      "id": "hungary",
      "name": "Hungary",
      "overall": 0.6084135468248939,
      "style": {}
    },
    {
      "attack": 0.25451174507695024,
      "defense": 0.3500412962890321,
      "elo": 1622.858302514058,
      "id": "jamaica",
      "name": "Jamaica",
      "overall": 0.6045530413659823,
      "style": {}
    },
    {
      "attack": 0.2252500130180414,
      "defense": 0.35963660560066263,
      "elo": 1683.1999521489715,
      "id": "republic-of-ireland",
      "name": "Republic of Ireland",
      "overall": 0.5848866186187041,
      "style": {}
    },
    {
      "attack": -0.019585316585554655,
      "defense": 0.6023193311430529,
      "elo": 1714.8638201945264,
      "id": "peru",
      "name": "Peru",
      "overall": 0.5827340145574983,
      "style": {}
    },
    {
      "attack": 0.35369323562051197,
      "defense": 0.22422843061454242,
      "elo": 1677.0314216711793,
      "id": "tunisia",
      "name": "Tunisia",
      "overall": 0.5779216662350544,
      "style": {}
    },
    {
      "attack": 0.3465513791247644,
      "defense": 0.2310150946188251,
      "elo": 1608.5163551771009,
      "id": "bolivia",
      "name": "Bolivia",
      "overall": 0.5775664737435895,
      "style": {}
    },
    {
      "attack": 0.3089378765045066,
      "defense": 0.2661801167636936,
      "elo": 1542.378962436914,
      "id": "suriname",
      "name": "Suriname",
      "overall": 0.5751179932682002,
      "style": {}
    },
    {
      "attack": 0.28268221330968496,
      "defense": 0.27308471615390456,
      "elo": 1402.1333711187847,
      "id": "raetia",
      "name": "Raetia",
      "overall": 0.5557669294635895,
      "style": {}
    },
    {
      "attack": 0.08521753650294252,
      "defense": 0.4632233879147146,
      "elo": 1685.696680355524,
      "id": "slovenia",
      "name": "Slovenia",
      "overall": 0.5484409244176571,
      "style": {}
    },
    {
      "attack": 0.3605543856338822,
      "defense": 0.1829070092111784,
      "elo": 1483.0278892529693,
      "id": "sz\u00e9kely-land",
      "name": "Sz\u00e9kely Land",
      "overall": 0.5434613948450606,
      "style": {}
    },
    {
      "attack": 0.40492110720350355,
      "defense": 0.1285424977770194,
      "elo": 1684.3937510728333,
      "id": "wales",
      "name": "Wales",
      "overall": 0.5334636049805229,
      "style": {}
    },
    {
      "attack": 0.4989386231599614,
      "defense": 0.02990126537492988,
      "elo": 1591.9073335492374,
      "id": "iceland",
      "name": "Iceland",
      "overall": 0.5288398885348913,
      "style": {}
    },
    {
      "attack": 0.16891785635694193,
      "defense": 0.3535628613279564,
      "elo": 1546.4487790956473,
      "id": "china",
      "name": "China",
      "overall": 0.5224807176848983,
      "style": {}
    },
    {
      "attack": 0.46502067685656534,
      "defense": 0.04820486147351527,
      "elo": 1574.980936438477,
      "id": "guatemala",
      "name": "Guatemala",
      "overall": 0.5132255383300806,
      "style": {}
    },
    {
      "attack": 0.16681310777387176,
      "defense": 0.332965909359019,
      "elo": 1577.9882622123432,
      "id": "oman",
      "name": "Oman",
      "overall": 0.49977901713289075,
      "style": {}
    },
    {
      "attack": 0.5170465516613308,
      "defense": -0.026338058177123598,
      "elo": 1741.8484350712974,
      "id": "basque-country",
      "name": "Basque Country",
      "overall": 0.49070849348420725,
      "style": {}
    },
    {
      "attack": 0.5590605388590966,
      "defense": -0.08626971000525804,
      "elo": 1629.2241493540866,
      "id": "israel",
      "name": "Israel",
      "overall": 0.4727908288538385,
      "style": {}
    },
    {
      "attack": 0.4005849155371036,
      "defense": 0.07210139348191998,
      "elo": 1540.9728581461623,
      "id": "thailand",
      "name": "Thailand",
      "overall": 0.4726863090190236,
      "style": {}
    },
    {
      "attack": 0.1341894373743926,
      "defense": 0.33754925030017774,
      "elo": 1536.7108736474174,
      "id": "palestine",
      "name": "Palestine",
      "overall": 0.47173868767457033,
      "style": {}
    },
    {
      "attack": 0.21577956647468607,
      "defense": 0.2547249713850393,
      "elo": 1618.7442098521665,
      "id": "cape-verde",
      "name": "Cape Verde",
      "overall": 0.47050453785972535,
      "style": {}
    },
    {
      "attack": 0.3918080773925787,
      "defense": 0.07578463859273737,
      "elo": 1624.3049959522777,
      "id": "burkina-faso",
      "name": "Burkina Faso",
      "overall": 0.4675927159853161,
      "style": {}
    },
    {
      "attack": 0.3185594558662063,
      "defense": 0.11568454203832625,
      "elo": 1587.1751485774193,
      "id": "new-caledonia",
      "name": "New Caledonia",
      "overall": 0.43424399790453255,
      "style": {}
    },
    {
      "attack": 0.28765337730962715,
      "defense": 0.14511375462456114,
      "elo": 1651.4601745719976,
      "id": "romania",
      "name": "Romania",
      "overall": 0.43276713193418825,
      "style": {}
    },
    {
      "attack": 0.09810391215920612,
      "defense": 0.32694597642243106,
      "elo": 1598.6749137309687,
      "id": "northern-ireland",
      "name": "Northern Ireland",
      "overall": 0.42504988858163717,
      "style": {}
    },
    {
      "attack": 0.4346396110427031,
      "defense": -0.02180330662333755,
      "elo": 1496.778117864858,
      "id": "shetland",
      "name": "Shetland",
      "overall": 0.41283630441936553,
      "style": {}
    },
    {
      "attack": 0.26813440603021543,
      "defense": 0.13760010660311536,
      "elo": 1663.5238512135527,
      "id": "slovakia",
      "name": "Slovakia",
      "overall": 0.4057345126333308,
      "style": {}
    },
    {
      "attack": 0.29942674067651553,
      "defense": 0.09727273512959381,
      "elo": 1504.3716921952728,
      "id": "vietnam",
      "name": "Vietnam",
      "overall": 0.3966994758061093,
      "style": {}
    },
    {
      "attack": 0.21070469241700612,
      "defense": 0.17888521602947557,
      "elo": 1530.1686304742327,
      "id": "bahrain",
      "name": "Bahrain",
      "overall": 0.38958990844648167,
      "style": {}
    },
    {
      "attack": 0.38933548992332034,
      "defense": -0.01716471797505458,
      "elo": 1570.2516979124573,
      "id": "qatar",
      "name": "Qatar",
      "overall": 0.37217077194826576,
      "style": {}
    },
    {
      "attack": -0.10443016329701357,
      "defense": 0.45841956904108294,
      "elo": 1492.7165935836128,
      "id": "zanzibar",
      "name": "Zanzibar",
      "overall": 0.35398940574406934,
      "style": {}
    },
    {
      "attack": 0.24442384679347506,
      "defense": 0.10290081362047243,
      "elo": 1550.1443124140303,
      "id": "guinea",
      "name": "Guinea",
      "overall": 0.3473246604139475,
      "style": {}
    },
    {
      "attack": 0.19675232791025973,
      "defense": 0.12524938168606603,
      "elo": 1511.7465238714342,
      "id": "benin",
      "name": "Benin",
      "overall": 0.3220017095963258,
      "style": {}
    },
    {
      "attack": 0.1007384764407617,
      "defense": 0.20304694805007725,
      "elo": 1558.401120294907,
      "id": "angola",
      "name": "Angola",
      "overall": 0.30378542449083895,
      "style": {}
    },
    {
      "attack": 0.20674409017540638,
      "defense": 0.07649199115108789,
      "elo": 1617.5316340698141,
      "id": "isle-of-wight",
      "name": "Isle of Wight",
      "overall": 0.28323608132649425,
      "style": {}
    },
    {
      "attack": 0.16853128756617383,
      "defense": 0.1048386299970992,
      "elo": 1486.1627636642474,
      "id": "indonesia",
      "name": "Indonesia",
      "overall": 0.273369917563273,
      "style": {}
    },
    {
      "attack": 0.3492558807379747,
      "defense": -0.07630912956611682,
      "elo": 1467.241150235269,
      "id": "dominican-republic",
      "name": "Dominican Republic",
      "overall": 0.27294675117185785,
      "style": {}
    },
    {
      "attack": 0.26732534536248065,
      "defense": 0.0053519641958269136,
      "elo": 1707.8016561893276,
      "id": "guernsey",
      "name": "Guernsey",
      "overall": 0.27267730955830755,
      "style": {}
    },
    {
      "attack": 0.2782876224668444,
      "defense": -0.01408771706379295,
      "elo": 1536.4102755872045,
      "id": "curacao",
      "name": "Curacao",
      "overall": 0.26419990540305144,
      "style": {}
    },
    {
      "attack": 0.1749539538223848,
      "defense": 0.07960786873152827,
      "elo": 1610.9434593630897,
      "id": "bosnia-herzegovina",
      "name": "Bosnia-Herzegovina",
      "overall": 0.2545618225539131,
      "style": {}
    },
    {
      "attack": -0.05423546138144575,
      "defense": 0.288497904364322,
      "elo": 1457.854609527218,
      "id": "lebanon",
      "name": "Lebanon",
      "overall": 0.23426244298287624,
      "style": {}
    },
    {
      "attack": -0.11079544500524346,
      "defense": 0.34226461202680974,
      "elo": 1458.8915349466754,
      "id": "rwanda",
      "name": "Rwanda",
      "overall": 0.23146916702156628,
      "style": {}
    },
    {
      "attack": 0.1720754341548308,
      "defense": 0.059277575613282264,
      "elo": 1525.012494881996,
      "id": "chameria",
      "name": "Chameria",
      "overall": 0.23135300976811304,
      "style": {}
    },
    {
      "attack": 0.08560692294935292,
      "defense": 0.13971787389527326,
      "elo": 1448.686235694954,
      "id": "tajikistan",
      "name": "Tajikistan",
      "overall": 0.2253247968446262,
      "style": {}
    },
    {
      "attack": 0.21385196992744365,
      "defense": 0.0081508179771114,
      "elo": 1419.6507064351345,
      "id": "orkney",
      "name": "Orkney",
      "overall": 0.22200278790455505,
      "style": {}
    },
    {
      "attack": 0.1697468280448578,
      "defense": 0.04963363300833873,
      "elo": 1511.828489702019,
      "id": "north-korea",
      "name": "North Korea",
      "overall": 0.21938046105319653,
      "style": {}
    },
    {
      "attack": 0.05638718915024851,
      "defense": 0.16180239558516465,
      "elo": 1514.1560396437599,
      "id": "elba-island",
      "name": "Elba Island",
      "overall": 0.21818958473541317,
      "style": {}
    },
    {
      "attack": 0.17830241128780694,
      "defense": 0.022358131363655016,
      "elo": 1497.137414846752,
      "id": "malaysia",
      "name": "Malaysia",
      "overall": 0.20066054265146197,
      "style": {}
    },
    {
      "attack": 0.003424670925622121,
      "defense": 0.19592629540612283,
      "elo": 1519.3876393477171,
      "id": "maule-sur",
      "name": "Maule Sur",
      "overall": 0.19935096633174496,
      "style": {}
    },
    {
      "attack": 0.22064055140155536,
      "defense": -0.02398152962389735,
      "elo": 1647.607903193607,
      "id": "padania",
      "name": "Padania",
      "overall": 0.196659021777658,
      "style": {}
    },
    {
      "attack": 0.12335399008724023,
      "defense": 0.06608940501833635,
      "elo": 1576.991247371668,
      "id": "kernow",
      "name": "Kernow",
      "overall": 0.18944339510557656,
      "style": {}
    },
    {
      "attack": -0.04409284342482453,
      "defense": 0.23306839926929768,
      "elo": 1437.4009208975106,
      "id": "saint-barth\u00e9lemy",
      "name": "Saint Barth\u00e9lemy",
      "overall": 0.18897555584447315,
      "style": {}
    },
    {
      "attack": 0.3605213853140203,
      "defense": -0.17386928168176694,
      "elo": 1500.5110753294935,
      "id": "gambia",
      "name": "Gambia",
      "overall": 0.18665210363225335,
      "style": {}
    },
    {
      "attack": 0.11121091194676791,
      "defense": 0.06369434181686924,
      "elo": 1587.6188413723637,
      "id": "abkhazia",
      "name": "Abkhazia",
      "overall": 0.17490525376363714,
      "style": {}
    },
    {
      "attack": 0.06398221217575586,
      "defense": 0.11049450707738699,
      "elo": 1578.0508833207546,
      "id": "finland",
      "name": "Finland",
      "overall": 0.17447671925314284,
      "style": {}
    },
    {
      "attack": 0.07682864726182176,
      "defense": 0.09424186533364488,
      "elo": 1555.854211165116,
      "id": "panjab",
      "name": "Panjab",
      "overall": 0.17107051259546663,
      "style": {}
    },
    {
      "attack": 0.07695839030025674,
      "defense": 0.09292324091293076,
      "elo": 1534.1022888990997,
      "id": "zambia",
      "name": "Zambia",
      "overall": 0.1698816312131875,
      "style": {}
    },
    {
      "attack": 0.1608717459374723,
      "defense": 0.008994453624010704,
      "elo": 1621.6766293708974,
      "id": "northern-cyprus",
      "name": "Northern Cyprus",
      "overall": 0.16986619956148302,
      "style": {}
    },
    {
      "attack": -0.03264928054380064,
      "defense": 0.1996657971282499,
      "elo": 1509.939262428248,
      "id": "biafra",
      "name": "Biafra",
      "overall": 0.16701651658444924,
      "style": {}
    },
    {
      "attack": -0.0017121654153620602,
      "defense": 0.1679803634216944,
      "elo": 1501.302241633163,
      "id": "mapuche",
      "name": "Mapuche",
      "overall": 0.16626819800633233,
      "style": {}
    },
    {
      "attack": -0.14615527386395213,
      "defense": 0.31201932960079237,
      "elo": 1587.8991608033484,
      "id": "albania",
      "name": "Albania",
      "overall": 0.16586405573684024,
      "style": {}
    },
    {
      "attack": 0.07381449441455458,
      "defense": 0.0920382559289669,
      "elo": 1482.5848922333594,
      "id": "zimbabwe",
      "name": "Zimbabwe",
      "overall": 0.16585275034352148,
      "style": {}
    },
    {
      "attack": 0.1362393692896137,
      "defense": 0.02517757108023716,
      "elo": 1440.9358000863874,
      "id": "niger",
      "name": "Niger",
      "overall": 0.16141694036985085,
      "style": {}
    },
    {
      "attack": 0.004383999101532254,
      "defense": 0.15603247294118786,
      "elo": 1510.383707758771,
      "id": "western-armenia",
      "name": "Western Armenia",
      "overall": 0.1604164720427201,
      "style": {}
    },
    {
      "attack": 0.005535346089160766,
      "defense": 0.15482355370070283,
      "elo": 1513.2594811841475,
      "id": "parishes-of-jersey",
      "name": "Parishes of Jersey",
      "overall": 0.1603588997898636,
      "style": {}
    },
    {
      "attack": 0.05882695679501713,
      "defense": 0.09874728440204347,
      "elo": 1554.2681557074168,
      "id": "k\u00e1rp\u00e1talja",
      "name": "K\u00e1rp\u00e1talja",
      "overall": 0.1575742411970606,
      "style": {}
    },
    {
      "attack": 0.03379527827057853,
      "defense": 0.1205812643143885,
      "elo": 1532.4432866383352,
      "id": "cascadia",
      "name": "Cascadia",
      "overall": 0.15437654258496702,
      "style": {}
    },
    {
      "attack": 0.04784650002983014,
      "defense": 0.10521675980103615,
      "elo": 1549.0299238018033,
      "id": "yorkshire",
      "name": "Yorkshire",
      "overall": 0.15306325983086627,
      "style": {}
    },
    {
      "attack": 0.052611427676867,
      "defense": 0.0938908957039271,
      "elo": 1555.5126251291033,
      "id": "ellan-vannin",
      "name": "Ellan Vannin",
      "overall": 0.1465023233807941,
      "style": {}
    },
    {
      "attack": -0.0660267832573964,
      "defense": 0.21179163726175845,
      "elo": 1472.205360217571,
      "id": "gotland",
      "name": "Gotland",
      "overall": 0.14576485400436207,
      "style": {}
    },
    {
      "attack": -0.016962836761896423,
      "defense": 0.16034583316156834,
      "elo": 1511.2237325796045,
      "id": "united-koreans-in-japan",
      "name": "United Koreans in Japan",
      "overall": 0.14338299639967192,
      "style": {}
    },
    {
      "attack": 0.1035465248574624,
      "defense": 0.038499208517187106,
      "elo": 1597.4825898034096,
      "id": "iraqi-kurdistan",
      "name": "Iraqi Kurdistan",
      "overall": 0.14204573337464949,
      "style": {}
    },
    {
      "attack": 0.1612617723557438,
      "defense": -0.021228545317998847,
      "elo": 1639.6752378355293,
      "id": "occitania",
      "name": "Occitania",
      "overall": 0.14003322703774496,
      "style": {}
    },
    {
      "attack": -0.051432317514770134,
      "defense": 0.19106502042544798,
      "elo": 1479.8615784448823,
      "id": "south-ossetia",
      "name": "South Ossetia",
      "overall": 0.13963270291067786,
      "style": {}
    },
    {
      "attack": -0.018906536943430672,
      "defense": 0.158442867203464,
      "elo": 1511.5521082552254,
      "id": "surrey",
      "name": "Surrey",
      "overall": 0.13953633026003334,
      "style": {}
    },
    {
      "attack": 0.5107497058636012,
      "defense": -0.3712817517907897,
      "elo": 1387.4337540042472,
      "id": "hitra",
      "name": "Hitra",
      "overall": 0.13946795407281154,
      "style": {}
    },
    {
      "attack": -0.0810983101510449,
      "defense": 0.22053861643798028,
      "elo": 1467.1261317127612,
      "id": "provence",
      "name": "Provence",
      "overall": 0.13944030628693538,
      "style": {}
    },
    {
      "attack": -0.004508674573376108,
      "defense": 0.14377985357159226,
      "elo": 1521.9829467192706,
      "id": "quebec",
      "name": "Quebec",
      "overall": 0.13927117899821614,
      "style": {}
    },
    {
      "attack": 0.031882844394324227,
      "defense": 0.10730794191960455,
      "elo": 1540.8508268458445,
      "id": "artsakh",
      "name": "Artsakh",
      "overall": 0.13919078631392878,
      "style": {}
    },
    {
      "attack": 0.039129779239440526,
      "defense": 0.10001228923457739,
      "elo": 1552.5308339973603,
      "id": "county-of-nice",
      "name": "County of Nice",
      "overall": 0.13914206847401792,
      "style": {}
    },
    {
      "attack": 0.13501342954457685,
      "defense": 0.004000432956373869,
      "elo": 1621.33649454913,
      "id": "catalonia",
      "name": "Catalonia",
      "overall": 0.1390138625009507,
      "style": {}
    },
    {
      "attack": -0.043136485706021736,
      "defense": 0.18178239593516057,
      "elo": 1492.5184928967817,
      "id": "franconia",
      "name": "Franconia",
      "overall": 0.13864591022913883,
      "style": {}
    },
    {
      "attack": -0.022725523501773783,
      "defense": 0.16130067381671115,
      "elo": 1509.4568323459564,
      "id": "donetsk-pr",
      "name": "Donetsk PR",
      "overall": 0.13857515031493736,
      "style": {}
    },
    {
      "attack": -0.037578954334409206,
      "defense": 0.17614364994428638,
      "elo": 1498.5242188501807,
      "id": "d\u00e9lvid\u00e9k",
      "name": "D\u00e9lvid\u00e9k",
      "overall": 0.13856469560987716,
      "style": {}
    },
    {
      "attack": 0.023615342042828318,
      "defense": 0.11491882291720554,
      "elo": 1542.5411501666263,
      "id": "kurdistan",
      "name": "Kurdistan",
      "overall": 0.13853416496003385,
      "style": {}
    },
    {
      "attack": 0.004433823916068625,
      "defense": 0.1339647512762865,
      "elo": 1528.8050168733334,
      "id": "arameans-suryoye",
      "name": "Arameans Suryoye",
      "overall": 0.1383985751923551,
      "style": {}
    },
    {
      "attack": 0.020330674249675117,
      "defense": 0.11795246999639575,
      "elo": 1540.4538869185333,
      "id": "corsica",
      "name": "Corsica",
      "overall": 0.13828314424607085,
      "style": {}
    },
    {
      "attack": 0.07364377479205207,
      "defense": 0.0643803129778937,
      "elo": 1578.3841279708217,
      "id": "andalusia",
      "name": "Andalusia",
      "overall": 0.1380240877699458,
      "style": {}
    },
    {
      "attack": 0.04208789816001797,
      "defense": 0.09592247398442555,
      "elo": 1555.9320326542029,
      "id": "rhodes",
      "name": "Rhodes",
      "overall": 0.1380103721444435,
      "style": {}
    },
    {
      "attack": -0.16581061052735382,
      "defense": 0.30380829576399127,
      "elo": 1407.9633439738473,
      "id": "yemen-dpr",
      "name": "Yemen DPR",
      "overall": 0.13799768523663744,
      "style": {}
    },
    {
      "attack": -0.024890032133356936,
      "defense": 0.16288652766923162,
      "elo": 1508.2739353734437,
      "id": "brittany",
      "name": "Brittany",
      "overall": 0.13799649553587467,
      "style": {}
    },
    {
      "attack": -0.15402124497511427,
      "defense": 0.29201741061009023,
      "elo": 1416.3545101252357,
      "id": "vietnam-republic",
      "name": "Vietnam Republic",
      "overall": 0.13799616563497596,
      "style": {}
    },
    {
      "attack": -0.017870916641450362,
      "defense": 0.15586581574167077,
      "elo": 1513.2648081744944,
      "id": "asturias",
      "name": "Asturias",
      "overall": 0.13799489910022042,
      "style": {}
    },
    {
      "attack": -0.041691903967393626,
      "defense": 0.17968660159760105,
      "elo": 1496.3084742619587,
      "id": "saugeais",
      "name": "Saugeais",
      "overall": 0.13799469763020744,
      "style": {}
    },
    {
      "attack": -0.03951640530725471,
      "defense": 0.1775080513519262,
      "elo": 1497.8589992651682,
      "id": "central-spain",
      "name": "Central Spain",
      "overall": 0.1379916460446715,
      "style": {}
    },
    {
      "attack": -0.24925511503870176,
      "defense": 0.3872463261383889,
      "elo": 1348.569845850988,
      "id": "wallis-islands-and-futuna",
      "name": "Wallis Islands and Futuna",
      "overall": 0.13799121109968712,
      "style": {}
    },
    {
      "attack": -0.18397840198119217,
      "defense": 0.3219690510150665,
      "elo": 1395.031563962062,
      "id": "sark",
      "name": "Sark",
      "overall": 0.13799064903387434,
      "style": {}
    },
    {
      "attack": 0.3076225687599047,
      "defense": -0.16963217627141988,
      "elo": 1744.9478062504509,
      "id": "yugoslavia",
      "name": "Yugoslavia",
      "overall": 0.1379903924884848,
      "style": {}
    },
    {
      "attack": -0.11847653986748452,
      "defense": 0.25646679759445246,
      "elo": 1441.6571692807008,
      "id": "palau",
      "name": "Palau",
      "overall": 0.13799025772696794,
      "style": {}
    },
    {
      "attack": -0.10595155038673609,
      "defense": 0.24394169902959312,
      "elo": 1450.5734063182288,
      "id": "saarland",
      "name": "Saarland",
      "overall": 0.13799014864285702,
      "style": {}
    },
    {
      "attack": -0.09723487944216386,
      "defense": 0.23522485222091663,
      "elo": 1456.7778967044203,
      "id": "niue",
      "name": "Niue",
      "overall": 0.13798997277875277,
      "style": {}
    },
    {
      "attack": 0.22690214758232927,
      "defense": -0.08891234803013343,
      "elo": 1687.490511896974,
      "id": "german-dr",
      "name": "German DR",
      "overall": 0.13798979955219584,
      "style": {}
    },
    {
      "attack": -0.1252115597377791,
      "defense": 0.2632012830106561,
      "elo": 1436.8640576685204,
      "id": "western-australia",
      "name": "Western Australia",
      "overall": 0.137989723272877,
      "style": {}
    },
    {
      "attack": -0.02055963685649232,
      "defense": 0.1585481805030755,
      "elo": 1511.353750478647,
      "id": "canary-islands",
      "name": "Canary Islands",
      "overall": 0.1379885436465832,
      "style": {}
    },
    {
      "attack": 0.27316007874620063,
      "defense": -0.13517164533684448,
      "elo": 1720.419844048696,
      "id": "czechoslovakia",
      "name": "Czechoslovakia",
      "overall": 0.13798843340935615,
      "style": {}
    },
    {
      "attack": -0.05281489752745797,
      "defense": 0.19080285072085082,
      "elo": 1488.396310104362,
      "id": "north-vietnam",
      "name": "North Vietnam",
      "overall": 0.13798795319339285,
      "style": {}
    },
    {
      "attack": -0.11791847438614747,
      "defense": 0.25590637147455225,
      "elo": 1442.0543033311524,
      "id": "manchukuo",
      "name": "Manchukuo",
      "overall": 0.13798789708840478,
      "style": {}
    },
    {
      "attack": -0.04748666305100724,
      "defense": 0.1854743901528087,
      "elo": 1492.1880024507063,
      "id": "cilento",
      "name": "Cilento",
      "overall": 0.13798772710180146,
      "style": {}
    },
    {
      "attack": -0.026332982196426602,
      "defense": 0.1643205686450865,
      "elo": 1507.244056430256,
      "id": "silesia",
      "name": "Silesia",
      "overall": 0.1379875864486599,
      "style": {}
    },
    {
      "attack": -0.05310293254331622,
      "defense": 0.19109030944058664,
      "elo": 1488.187675167615,
      "id": "republic-of-st.-pauli",
      "name": "Republic of St. Pauli",
      "overall": 0.13798737689727042,
      "style": {}
    },
    {
      "attack": -0.06208212058985928,
      "defense": 0.20006938872139876,
      "elo": 1481.7974483608093,
      "id": "south-yemen",
      "name": "South Yemen",
      "overall": 0.1379872681315395,
      "style": {}
    },
    {
      "attack": -0.1817490840153042,
      "defense": 0.31973519076024165,
      "elo": 1396.6198704187782,
      "id": "micronesia",
      "name": "Micronesia",
      "overall": 0.13798610674493744,
      "style": {}
    },
    {
      "attack": -0.031859441115032236,
      "defense": 0.16984535705120343,
      "elo": 1503.310533113127,
      "id": "crimea",
      "name": "Crimea",
      "overall": 0.1379859159361712,
      "style": {}
    },
    {
      "attack": -0.09074534834859214,
      "defense": 0.22872942913385064,
      "elo": 1461.3975270234753,
      "id": "g\u0103g\u0103uzia",
      "name": "G\u0103g\u0103uzia",
      "overall": 0.13798408078525848,
      "style": {}
    },
    {
      "attack": -0.12387698166257197,
      "defense": 0.26186085517854096,
      "elo": 1437.8133062715729,
      "id": "ambazonia",
      "name": "Ambazonia",
      "overall": 0.137983873515969,
      "style": {}
    },
    {
      "attack": -0.09951879668340431,
      "defense": 0.2375026468129192,
      "elo": 1455.1524462140783,
      "id": "chechnya",
      "name": "Chechnya",
      "overall": 0.13798385012951486,
      "style": {}
    },
    {
      "attack": -0.05042272531100758,
      "defense": 0.188383164615164,
      "elo": 1490.1002861375655,
      "id": "madrid",
      "name": "Madrid",
      "overall": 0.1379604393041564,
      "style": {}
    },
    {
      "attack": -0.053645947766500564,
      "defense": 0.19157267592778687,
      "elo": 1487.7791735225103,
      "id": "seborga",
      "name": "Seborga",
      "overall": 0.13792672816128632,
      "style": {}
    },
    {
      "attack": -0.03767275233345634,
      "defense": 0.17550740067672804,
      "elo": 1498.7539790188378,
      "id": "sealand",
      "name": "Sealand",
      "overall": 0.1378346483432717,
      "style": {}
    },
    {
      "attack": -0.1037663873041907,
      "defense": 0.24146876056718364,
      "elo": 1452.2564535161714,
      "id": "monaco",
      "name": "Monaco",
      "overall": 0.13770237326299295,
      "style": {}
    },
    {
      "attack": -0.27988905874298436,
      "defense": 0.4171284914537491,
      "elo": 1326.832333838692,
      "id": "kiribati",
      "name": "Kiribati",
      "overall": 0.13723943271076472,
      "style": {}
    },
    {
      "attack": -0.035254741353708645,
      "defense": 0.17240651274107469,
      "elo": 1500.47025492479,
      "id": "felvid\u00e9k",
      "name": "Felvid\u00e9k",
      "overall": 0.13715177138736603,
      "style": {}
    },
    {
      "attack": -0.12174911834485032,
      "defense": 0.2586196445495063,
      "elo": 1439.300980762121,
      "id": "western-sahara",
      "name": "Western Sahara",
      "overall": 0.136870526204656,
      "style": {}
    },
    {
      "attack": -0.04615619126231469,
      "defense": 0.1826883975361365,
      "elo": 1490.4468657069388,
      "id": "luhansk-pr",
      "name": "Luhansk PR",
      "overall": 0.13653220627382182,
      "style": {}
    },
    {
      "attack": -0.08050578336526734,
      "defense": 0.21700000227565364,
      "elo": 1468.2257803711277,
      "id": "romani-people",
      "name": "Romani people",
      "overall": 0.1364942189103863,
      "style": {}
    },
    {
      "attack": 0.21386160877513416,
      "defense": -0.07745742230303818,
      "elo": 1481.57228955991,
      "id": "kuwait",
      "name": "Kuwait",
      "overall": 0.13640418647209598,
      "style": {}
    },
    {
      "attack": -0.21722610157553868,
      "defense": 0.353321992027171,
      "elo": 1369.4033796583087,
      "id": "saare-county",
      "name": "Saare County",
      "overall": 0.13609589045163234,
      "style": {}
    },
    {
      "attack": -0.23431214188399432,
      "defense": 0.37036562222831837,
      "elo": 1359.38063309493,
      "id": "saint-pierre-and-miquelon",
      "name": "Saint Pierre and Miquelon",
      "overall": 0.13605348034432405,
      "style": {}
    },
    {
      "attack": -0.06974711536048285,
      "defense": 0.20545177522063296,
      "elo": 1476.6200350080844,
      "id": "ry\u016bky\u016b",
      "name": "Ry\u016bky\u016b",
      "overall": 0.13570465986015012,
      "style": {}
    },
    {
      "attack": -0.05532891449971799,
      "defense": 0.18732448469896734,
      "elo": 1484.355134716441,
      "id": "somaliland",
      "name": "Somaliland",
      "overall": 0.13199557019924935,
      "style": {}
    },
    {
      "attack": -0.2434051705798858,
      "defense": 0.3734685528022512,
      "elo": 1353.5058689549935,
      "id": "darfur",
      "name": "Darfur",
      "overall": 0.1300633822223654,
      "style": {}
    },
    {
      "attack": -0.19111371223842888,
      "defense": 0.31989716094211984,
      "elo": 1454.4046035305118,
      "id": "mayotte",
      "name": "Mayotte",
      "overall": 0.12878344870369096,
      "style": {}
    },
    {
      "attack": -0.06653896820048433,
      "defense": 0.19445433795030387,
      "elo": 1477.0097078328602,
      "id": "west-papua",
      "name": "West Papua",
      "overall": 0.12791536974981954,
      "style": {}
    },
    {
      "attack": -0.06420938212158811,
      "defense": 0.19097499988928174,
      "elo": 1489.1179024004773,
      "id": "matabeleland",
      "name": "Matabeleland",
      "overall": 0.12676561776769363,
      "style": {}
    },
    {
      "attack": -0.07116556971136336,
      "defense": 0.19570544105869783,
      "elo": 1473.7301565688103,
      "id": "kabylia",
      "name": "Kabylia",
      "overall": 0.12453987134733448,
      "style": {}
    },
    {
      "attack": -0.3446672460125973,
      "defense": 0.4638696683325001,
      "elo": 1285.2144253944543,
      "id": "eritrea",
      "name": "Eritrea",
      "overall": 0.1192024223199028,
      "style": {}
    },
    {
      "attack": -0.12966511806366438,
      "defense": 0.2485521702722995,
      "elo": 1427.2392085947033,
      "id": "vatican-city",
      "name": "Vatican City",
      "overall": 0.11888705220863513,
      "style": {}
    },
    {
      "attack": 0.010521435176197252,
      "defense": 0.10662199264346275,
      "elo": 1575.1170155725547,
      "id": "r\u00e9union",
      "name": "R\u00e9union",
      "overall": 0.11714342781966,
      "style": {}
    },
    {
      "attack": -0.07044547210524676,
      "defense": 0.17913276630285666,
      "elo": 1489.3798445973337,
      "id": "yoruba-nation",
      "name": "Yoruba Nation",
      "overall": 0.10868729419760989,
      "style": {}
    },
    {
      "attack": -0.17774628898819547,
      "defense": 0.27335733730621115,
      "elo": 1400.9214463536935,
      "id": "barawa",
      "name": "Barawa",
      "overall": 0.09561104831801567,
      "style": {}
    },
    {
      "attack": 0.09809649668929049,
      "defense": -0.005932606147467533,
      "elo": 1502.7208794992016,
      "id": "uganda",
      "name": "Uganda",
      "overall": 0.09216389054182296,
      "style": {}
    },
    {
      "attack": -0.18732289346715428,
      "defense": 0.26703053800893395,
      "elo": 1392.3152731417754,
      "id": "chagos-islands",
      "name": "Chagos Islands",
      "overall": 0.07970764454177967,
      "style": {}
    },
    {
      "attack": 0.11217819499432642,
      "defense": -0.033281293831053806,
      "elo": 1545.057591551491,
      "id": "menorca",
      "name": "Menorca",
      "overall": 0.07889690116327261,
      "style": {}
    },
    {
      "attack": 0.10827504077545917,
      "defense": -0.042683894268883374,
      "elo": 1538.751362903166,
      "id": "tahiti",
      "name": "Tahiti",
      "overall": 0.0655911465065758,
      "style": {}
    },
    {
      "attack": -0.04340330618567472,
      "defense": 0.10796144422747521,
      "elo": 1492.9443747348773,
      "id": "s\u00e1pmi",
      "name": "S\u00e1pmi",
      "overall": 0.0645581380418005,
      "style": {}
    },
    {
      "attack": -0.022131394516843983,
      "defense": 0.08666867445378666,
      "elo": 1465.9288337981445,
      "id": "nicaragua",
      "name": "Nicaragua",
      "overall": 0.06453727993694268,
      "style": {}
    },
    {
      "attack": -0.00951510963468604,
      "defense": 0.07126477615102887,
      "elo": 1528.6678166552374,
      "id": "libya",
      "name": "Libya",
      "overall": 0.06174966651634283,
      "style": {}
    },
    {
      "attack": 0.17686583899379021,
      "defense": -0.11837876897322894,
      "elo": 1515.7169163150672,
      "id": "guadeloupe",
      "name": "Guadeloupe",
      "overall": 0.05848707002056128,
      "style": {}
    },
    {
      "attack": -0.05483989498735916,
      "defense": 0.10790380162039062,
      "elo": 1522.2344314741144,
      "id": "galicia",
      "name": "Galicia",
      "overall": 0.05306390663303146,
      "style": {}
    },
    {
      "attack": -0.09134894908044233,
      "defense": 0.13973412911826794,
      "elo": 1479.3101190191198,
      "id": "aymara",
      "name": "Aymara",
      "overall": 0.048385180037825604,
      "style": {}
    },
    {
      "attack": 0.40642210667890705,
      "defense": -0.36219699673610045,
      "elo": 1333.0986072130943,
      "id": "yemen",
      "name": "Yemen",
      "overall": 0.044225109942806595,
      "style": {}
    },
    {
      "attack": 0.058747392420255895,
      "defense": -0.026797884460379017,
      "elo": 1436.7817995088988,
      "id": "kyrgyzstan",
      "name": "Kyrgyzstan",
      "overall": 0.031949507959876874,
      "style": {}
    },
    {
      "attack": 0.2282830515581965,
      "defense": -0.22097720898883272,
      "elo": 1523.5104484939686,
      "id": "bulgaria",
      "name": "Bulgaria",
      "overall": 0.007305842569363785,
      "style": {}
    },
    {
      "attack": 0.008488302911111995,
      "defense": -0.010209112392552403,
      "elo": 1485.2649735062948,
      "id": "togo",
      "name": "Togo",
      "overall": -0.0017208094814404086,
      "style": {}
    },
    {
      "attack": -0.18071979446027592,
      "defense": 0.1746410867124977,
      "elo": 1494.677129742645,
      "id": "el-salvador",
      "name": "El Salvador",
      "overall": -0.006078707747778217,
      "style": {}
    },
    {
      "attack": -0.06092660053690211,
      "defense": 0.03226007104362529,
      "elo": 1484.209788433103,
      "id": "gozo",
      "name": "Gozo",
      "overall": -0.02866652949327682,
      "style": {}
    },
    {
      "attack": -0.22361668548379585,
      "defense": 0.18683572390095116,
      "elo": 1421.7261111870043,
      "id": "tanzania",
      "name": "Tanzania",
      "overall": -0.03678096158284469,
      "style": {}
    },
    {
      "attack": 0.08954275792661762,
      "defense": -0.1286555340775633,
      "elo": 1546.4489814237854,
      "id": "belarus",
      "name": "Belarus",
      "overall": -0.03911277615094569,
      "style": {}
    },
    {
      "attack": 0.15911375794127955,
      "defense": -0.2102658634102072,
      "elo": 1475.8643167898574,
      "id": "madagascar",
      "name": "Madagascar",
      "overall": -0.05115210546892765,
      "style": {}
    },
    {
      "attack": 0.1689048417756003,
      "defense": -0.22138241293102184,
      "elo": 1514.0976939004968,
      "id": "trinidad-and-tobago",
      "name": "Trinidad and Tobago",
      "overall": -0.05247757115542154,
      "style": {}
    },
    {
      "attack": 0.05081706371017555,
      "defense": -0.10536820351552986,
      "elo": 1452.954397444485,
      "id": "western-isles",
      "name": "Western Isles",
      "overall": -0.05455113980535431,
      "style": {}
    },
    {
      "attack": 0.2020657456431399,
      "defense": -0.263841721280516,
      "elo": 1521.6802583678286,
      "id": "gabon",
      "name": "Gabon",
      "overall": -0.06177597563737608,
      "style": {}
    },
    {
      "attack": 0.0668495175942786,
      "defense": -0.1293630104003104,
      "elo": 1481.2075244192215,
      "id": "hmong",
      "name": "Hmong",
      "overall": -0.0625134928060318,
      "style": {}
    },
    {
      "attack": 0.06438542032407732,
      "defense": -0.14608458343790756,
      "elo": 1369.261806674452,
      "id": "philippines",
      "name": "Philippines",
      "overall": -0.08169916311383024,
      "style": {}
    },
    {
      "attack": -0.5930874634966966,
      "defense": 0.5018892062956306,
      "elo": 1134.6743843403724,
      "id": "alderney",
      "name": "Alderney",
      "overall": -0.091198257201066,
      "style": {}
    },
    {
      "attack": 0.1261708030455475,
      "defense": -0.21964814730932622,
      "elo": 1468.0568791550954,
      "id": "mozambique",
      "name": "Mozambique",
      "overall": -0.09347734426377871,
      "style": {}
    },
    {
      "attack": 0.25383817562562005,
      "defense": -0.3528957606643993,
      "elo": 1475.879073505444,
      "id": "guyana",
      "name": "Guyana",
      "overall": -0.09905758503877926,
      "style": {}
    },
    {
      "attack": 0.035914534258005386,
      "defense": -0.1545083879564072,
      "elo": 1415.3535907274863,
      "id": "turkmenistan",
      "name": "Turkmenistan",
      "overall": -0.11859385369840181,
      "style": {}
    },
    {
      "attack": -0.021816744876629674,
      "defense": -0.10740360928812302,
      "elo": 1377.2892333576604,
      "id": "puerto-rico",
      "name": "Puerto Rico",
      "overall": -0.1292203541647527,
      "style": {}
    },
    {
      "attack": -0.04385325868071267,
      "defense": -0.09183620363311554,
      "elo": 1469.6398602512197,
      "id": "comoros",
      "name": "Comoros",
      "overall": -0.13568946231382822,
      "style": {}
    },
    {
      "attack": -0.010429072653394697,
      "defense": -0.18605228124653736,
      "elo": 1363.783804941377,
      "id": "hong-kong",
      "name": "Hong Kong",
      "overall": -0.19648135389993204,
      "style": {}
    },
    {
      "attack": -0.13144655904147431,
      "defense": -0.06709332844755489,
      "elo": 1581.9061883434772,
      "id": "north-macedonia",
      "name": "North Macedonia",
      "overall": -0.1985398874890292,
      "style": {}
    },
    {
      "attack": 0.4891614547725659,
      "defense": -0.7177839116532617,
      "elo": 1484.094795215354,
      "id": "east-turkestan",
      "name": "East Turkestan",
      "overall": -0.22862245688069582,
      "style": {}
    },
    {
      "attack": 0.28858650113717754,
      "defense": -0.5198511738327327,
      "elo": 1489.8231773209882,
      "id": "\u00e5land-islands",
      "name": "\u00c5land Islands",
      "overall": -0.23126467269555517,
      "style": {}
    },
    {
      "attack": -0.0631275283730553,
      "defense": -0.17701261105718058,
      "elo": 1458.2357317330784,
      "id": "french-guiana",
      "name": "French Guiana",
      "overall": -0.24014013943023588,
      "style": {}
    },
    {
      "attack": -0.10258435075493497,
      "defense": -0.1472453274685918,
      "elo": 1457.2893996548028,
      "id": "greenland",
      "name": "Greenland",
      "overall": -0.24982967822352678,
      "style": {}
    },
    {
      "attack": -0.40298205349785343,
      "defense": 0.14341493018621806,
      "elo": 1456.2741138077188,
      "id": "sudan",
      "name": "Sudan",
      "overall": -0.25956712331163534,
      "style": {}
    },
    {
      "attack": -0.1334907166858566,
      "defense": -0.15683737590276786,
      "elo": 1302.5258877590684,
      "id": "tuvalu",
      "name": "Tuvalu",
      "overall": -0.29032809258862446,
      "style": {}
    },
    {
      "attack": -0.1467265410171405,
      "defense": -0.1907644564581041,
      "elo": 1482.7684577541538,
      "id": "kenya",
      "name": "Kenya",
      "overall": -0.3374909974752446,
      "style": {}
    },
    {
      "attack": -0.14915731563012355,
      "defense": -0.2217393244808541,
      "elo": 1453.7340524386073,
      "id": "ticino",
      "name": "Ticino",
      "overall": -0.37089664011097767,
      "style": {}
    },
    {
      "attack": -0.1876474313118217,
      "defense": -0.18374287126247574,
      "elo": 1451.941589227684,
      "id": "two-sicilies",
      "name": "Two Sicilies",
      "overall": -0.37139030257429745,
      "style": {}
    },
    {
      "attack": -0.27033496163775894,
      "defense": -0.10723223023792348,
      "elo": 1451.5838279953848,
      "id": "equatorial-guinea",
      "name": "Equatorial Guinea",
      "overall": -0.37756719187568244,
      "style": {}
    },
    {
      "attack": -0.4865204301328479,
      "defense": 0.09194045416022363,
      "elo": 1465.0720203049923,
      "id": "mauritania",
      "name": "Mauritania",
      "overall": -0.3945799759726243,
      "style": {}
    },
    {
      "attack": -0.2546633513466958,
      "defense": -0.1657204549055337,
      "elo": 1462.0761712058033,
      "id": "kazakhstan",
      "name": "Kazakhstan",
      "overall": -0.4203838062522295,
      "style": {}
    },
    {
      "attack": -0.38570095299293533,
      "defense": -0.04703510019792267,
      "elo": 1490.025821593777,
      "id": "martinique",
      "name": "Martinique",
      "overall": -0.432736053190858,
      "style": {}
    },
    {
      "attack": -0.2035248897163451,
      "defense": -0.23203914749386162,
      "elo": 1448.5997695231174,
      "id": "sierra-leone",
      "name": "Sierra Leone",
      "overall": -0.43556403721020676,
      "style": {}
    },
    {
      "attack": -0.4414357609226633,
      "defense": 0.005440587851041172,
      "elo": 1302.7284055225612,
      "id": "falkland-islands",
      "name": "Falkland Islands",
      "overall": -0.4359951730716221,
      "style": {}
    },
    {
      "attack": -0.1095219330145176,
      "defense": -0.33852774240168687,
      "elo": 1341.6759926022135,
      "id": "singapore",
      "name": "Singapore",
      "overall": -0.44804967541620444,
      "style": {}
    },
    {
      "attack": -0.13155846678655136,
      "defense": -0.3253813736659315,
      "elo": 1332.4158869804048,
      "id": "saint-martin",
      "name": "Saint Martin",
      "overall": -0.45693984045248287,
      "style": {}
    },
    {
      "attack": -0.17876655503981656,
      "defense": -0.294614314806821,
      "elo": 1527.6298393588024,
      "id": "montenegro",
      "name": "Montenegro",
      "overall": -0.4733808698466375,
      "style": {}
    },
    {
      "attack": -0.2172938868070213,
      "defense": -0.27331203467332815,
      "elo": 1421.6387368704227,
      "id": "ethiopia",
      "name": "Ethiopia",
      "overall": -0.4906059214803494,
      "style": {}
    },
    {
      "attack": -0.23239300170635116,
      "defense": -0.262017221876086,
      "elo": 1407.4872421440762,
      "id": "liberia",
      "name": "Liberia",
      "overall": -0.49441022358243714,
      "style": {}
    },
    {
      "attack": -0.46315936868468033,
      "defense": -0.07072830400912768,
      "elo": 1420.8902564605298,
      "id": "burundi",
      "name": "Burundi",
      "overall": -0.533887672693808,
      "style": {}
    },
    {
      "attack": -0.44623978988277535,
      "defense": -0.09136451256367499,
      "elo": 1393.1200749081647,
      "id": "lesotho",
      "name": "Lesotho",
      "overall": -0.5376043024464503,
      "style": {}
    },
    {
      "attack": -0.27063634579402623,
      "defense": -0.2781864971773394,
      "elo": 1411.998196059045,
      "id": "azerbaijan",
      "name": "Azerbaijan",
      "overall": -0.5488228429713656,
      "style": {}
    },
    {
      "attack": -0.3323868450531529,
      "defense": -0.21751327814062538,
      "elo": 1446.696905574039,
      "id": "estonia",
      "name": "Estonia",
      "overall": -0.5499001231937783,
      "style": {}
    },
    {
      "attack": -0.25692946502116676,
      "defense": -0.2982303495595853,
      "elo": 1424.8441677930969,
      "id": "cuba",
      "name": "Cuba",
      "overall": -0.555159814580752,
      "style": {}
    },
    {
      "attack": -0.4211295607319735,
      "defense": -0.17871396080565483,
      "elo": 1434.9999330414837,
      "id": "malawi",
      "name": "Malawi",
      "overall": -0.5998435215376283,
      "style": {}
    },
    {
      "attack": -0.24651399924219394,
      "defense": -0.35653411025050796,
      "elo": 1162.0898527305114,
      "id": "cambodia",
      "name": "Cambodia",
      "overall": -0.6030481094927019,
      "style": {}
    },
    {
      "attack": -0.4593939098506906,
      "defense": -0.1909576095113071,
      "elo": 1422.6894231333742,
      "id": "botswana",
      "name": "Botswana",
      "overall": -0.6503515193619978,
      "style": {}
    },
    {
      "attack": -0.5081912527405923,
      "defense": -0.15289908939823485,
      "elo": 1392.9023892992245,
      "id": "faroe-islands",
      "name": "Faroe Islands",
      "overall": -0.6610903421388271,
      "style": {}
    },
    {
      "attack": -0.09955730317321697,
      "defense": -0.5623459501645878,
      "elo": 1394.3057566718817,
      "id": "central-african-republic",
      "name": "Central African Republic",
      "overall": -0.6619032533378048,
      "style": {}
    },
    {
      "attack": -0.5833173631865425,
      "defense": -0.0862655583271527,
      "elo": 1393.7031978296493,
      "id": "guinea-bissau",
      "name": "Guinea-Bissau",
      "overall": -0.6695829215136951,
      "style": {}
    },
    {
      "attack": -0.3143365373047142,
      "defense": -0.36616208412171397,
      "elo": 1481.506369465748,
      "id": "papua-new-guinea",
      "name": "Papua New Guinea",
      "overall": -0.6804986214264281,
      "style": {}
    },
    {
      "attack": -0.0778624820067973,
      "defense": -0.6074619657607876,
      "elo": 1395.523675648483,
      "id": "saint-vincent-and-the-grenadines",
      "name": "Saint Vincent and the Grenadines",
      "overall": -0.6853244477675848,
      "style": {}
    },
    {
      "attack": -0.29313557179263316,
      "defense": -0.40023639984981035,
      "elo": 1389.4030471659964,
      "id": "cyprus",
      "name": "Cyprus",
      "overall": -0.6933719716424436,
      "style": {}
    },
    {
      "attack": 0.04917370782461545,
      "defense": -0.7507838371014041,
      "elo": 1387.1617268570249,
      "id": "bermuda",
      "name": "Bermuda",
      "overall": -0.7016101292767886,
      "style": {}
    },
    {
      "attack": -0.23073089353902218,
      "defense": -0.5616629247468371,
      "elo": 1478.15280602974,
      "id": "vanuatu",
      "name": "Vanuatu",
      "overall": -0.7923938182858593,
      "style": {}
    },
    {
      "attack": -0.8055481651859968,
      "defense": 0.011303517953091426,
      "elo": 1436.543087929178,
      "id": "luxembourg",
      "name": "Luxembourg",
      "overall": -0.7942446472329053,
      "style": {}
    },
    {
      "attack": -0.5258774757142654,
      "defense": -0.2758617993967304,
      "elo": 1444.460046231291,
      "id": "namibia",
      "name": "Namibia",
      "overall": -0.8017392751109957,
      "style": {}
    },
    {
      "attack": 0.10576215567237371,
      "defense": -0.9121980223685049,
      "elo": 1327.2114832144325,
      "id": "tibet",
      "name": "Tibet",
      "overall": -0.8064358666961312,
      "style": {}
    },
    {
      "attack": -0.2539443366239816,
      "defense": -0.5550371203918828,
      "elo": 1337.978451722683,
      "id": "belize",
      "name": "Belize",
      "overall": -0.8089814570158644,
      "style": {}
    },
    {
      "attack": -0.37174573927735066,
      "defense": -0.4503756561126,
      "elo": 1407.03196476044,
      "id": "saint-helena",
      "name": "Saint Helena",
      "overall": -0.8221213953899507,
      "style": {}
    },
    {
      "attack": -0.20972540551467558,
      "defense": -0.6275604205728409,
      "elo": 1484.0000815214125,
      "id": "fiji",
      "name": "Fiji",
      "overall": -0.8372858260875164,
      "style": {}
    },
    {
      "attack": -0.3395563097266474,
      "defense": -0.4980892286855532,
      "elo": 1434.4249581506629,
      "id": "armenia",
      "name": "Armenia",
      "overall": -0.8376455384122006,
      "style": {}
    },
    {
      "attack": -0.260103012241543,
      "defense": -0.5793538979791241,
      "elo": 1274.5172684371123,
      "id": "aruba",
      "name": "Aruba",
      "overall": -0.839456910220667,
      "style": {}
    },
    {
      "attack": -0.38685840598455196,
      "defense": -0.5045894538845888,
      "elo": 1351.7328596403804,
      "id": "eswatini",
      "name": "Eswatini",
      "overall": -0.8914478598691407,
      "style": {}
    },
    {
      "attack": -0.17171874855817806,
      "defense": -0.7426832757324001,
      "elo": 1218.529518061503,
      "id": "myanmar",
      "name": "Myanmar",
      "overall": -0.9144020242905782,
      "style": {}
    },
    {
      "attack": -0.23417837747579523,
      "defense": -0.6804041480454557,
      "elo": 1357.539490353835,
      "id": "sint-maarten",
      "name": "Sint Maarten",
      "overall": -0.914582525521251,
      "style": {}
    },
    {
      "attack": -0.8277613660973128,
      "defense": -0.13899774517853097,
      "elo": 1331.058140855512,
      "id": "india",
      "name": "India",
      "overall": -0.9667591112758438,
      "style": {}
    },
    {
      "attack": -0.538409322692256,
      "defense": -0.43025681078519235,
      "elo": 1384.3031573064266,
      "id": "congo",
      "name": "Congo",
      "overall": -0.9686661334774485,
      "style": {}
    },
    {
      "attack": -0.7488868226667147,
      "defense": -0.2322402385121971,
      "elo": 1353.7156625969808,
      "id": "lithuania",
      "name": "Lithuania",
      "overall": -0.9811270611789118,
      "style": {}
    },
    {
      "attack": -0.39964333693483756,
      "defense": -0.6052514457511297,
      "elo": 1212.874346758761,
      "id": "tonga",
      "name": "Tonga",
      "overall": -1.0048947826859673,
      "style": {}
    },
    {
      "attack": -0.5840433881588342,
      "defense": -0.4824381469107501,
      "elo": 1147.3522231536235,
      "id": "northern-mariana-islands",
      "name": "Northern Mariana Islands",
      "overall": -1.0664815350695842,
      "style": {}
    },
    {
      "attack": -0.5816222738595188,
      "defense": -0.5212823459309448,
      "elo": 1334.3627416910147,
      "id": "moldova",
      "name": "Moldova",
      "overall": -1.1029046197904635,
      "style": {}
    },
    {
      "attack": -0.5240895570237297,
      "defense": -0.5883032532747321,
      "elo": 1171.6343979115334,
      "id": "pakistan",
      "name": "Pakistan",
      "overall": -1.112392810298462,
      "style": {}
    },
    {
      "attack": -0.7403312586801112,
      "defense": -0.37647124841195806,
      "elo": 1352.9860121903832,
      "id": "malta",
      "name": "Malta",
      "overall": -1.1168025070920693,
      "style": {}
    },
    {
      "attack": -0.3459290032741604,
      "defense": -0.7734070146959071,
      "elo": 1206.1345235724589,
      "id": "taiwan",
      "name": "Taiwan",
      "overall": -1.1193360179700675,
      "style": {}
    },
    {
      "attack": -0.27577736888312576,
      "defense": -0.8622739426851336,
      "elo": 1312.5893168523212,
      "id": "samoa",
      "name": "Samoa",
      "overall": -1.1380513115682593,
      "style": {}
    },
    {
      "attack": -0.4330745192211947,
      "defense": -0.7114142826441743,
      "elo": 1320.0521326155665,
      "id": "grenada",
      "name": "Grenada",
      "overall": -1.144488801865369,
      "style": {}
    },
    {
      "attack": -0.6698130185290013,
      "defense": -0.48004030442141715,
      "elo": 1295.7559572928376,
      "id": "montserrat",
      "name": "Montserrat",
      "overall": -1.1498533229504184,
      "style": {}
    },
    {
      "attack": -0.7783130073027316,
      "defense": -0.3909373202568797,
      "elo": 1265.181097962619,
      "id": "mauritius",
      "name": "Mauritius",
      "overall": -1.1692503275596113,
      "style": {}
    },
    {
      "attack": -0.7859744703043782,
      "defense": -0.3953803621818659,
      "elo": 1356.1263766198383,
      "id": "latvia",
      "name": "Latvia",
      "overall": -1.1813548324862442,
      "style": {}
    },
    {
      "attack": -0.5992263131392384,
      "defense": -0.595189211030117,
      "elo": 1210.0276745272315,
      "id": "bangladesh",
      "name": "Bangladesh",
      "overall": -1.1944155241693553,
      "style": {}
    },
    {
      "attack": -0.19963716102004037,
      "defense": -0.9964572330420349,
      "elo": 1449.5229984571602,
      "id": "solomon-islands",
      "name": "Solomon Islands",
      "overall": -1.1960943940620754,
      "style": {}
    },
    {
      "attack": -0.3307645900904416,
      "defense": -0.9108505843966666,
      "elo": 1458.2313018134116,
      "id": "marshall-islands",
      "name": "Marshall Islands",
      "overall": -1.2416151744871082,
      "style": {}
    },
    {
      "attack": -0.5401951043811603,
      "defense": -0.7039992942960669,
      "elo": 1262.4425833713383,
      "id": "bonaire",
      "name": "Bonaire",
      "overall": -1.244194398677227,
      "style": {}
    },
    {
      "attack": -0.9842666532510639,
      "defense": -0.2650795182387265,
      "elo": 1109.1883011705404,
      "id": "sri-lanka",
      "name": "Sri Lanka",
      "overall": -1.2493461714897904,
      "style": {}
    },
    {
      "attack": -0.3121137088564169,
      "defense": -0.9418926688366708,
      "elo": 1241.4971248912761,
      "id": "barbados",
      "name": "Barbados",
      "overall": -1.2540063776930876,
      "style": {}
    },
    {
      "attack": -0.33219725646799475,
      "defense": -0.9337065282850316,
      "elo": 1348.9234842682697,
      "id": "saint-kitts-and-nevis",
      "name": "Saint Kitts and Nevis",
      "overall": -1.2659037847530263,
      "style": {}
    },
    {
      "attack": -0.9745071353657919,
      "defense": -0.31226131924234657,
      "elo": 1210.4544011728267,
      "id": "nepal",
      "name": "Nepal",
      "overall": -1.2867684546081386,
      "style": {}
    },
    {
      "attack": -0.803670475494566,
      "defense": -0.5078482940347947,
      "elo": 1307.3199025989163,
      "id": "chad",
      "name": "Chad",
      "overall": -1.3115187695293606,
      "style": {}
    },
    {
      "attack": -0.7205540580129625,
      "defense": -0.5993045491610652,
      "elo": 1273.2668876529242,
      "id": "cook-islands",
      "name": "Cook Islands",
      "overall": -1.3198586071740277,
      "style": {}
    },
    {
      "attack": -0.6805450587900777,
      "defense": -0.6523637369802469,
      "elo": 1260.0360734117291,
      "id": "dominica",
      "name": "Dominica",
      "overall": -1.3329087957703245,
      "style": {}
    },
    {
      "attack": -0.9009959737164195,
      "defense": -0.4504510827231795,
      "elo": 1308.4381384852945,
      "id": "south-sudan",
      "name": "South Sudan",
      "overall": -1.351447056439599,
      "style": {}
    },
    {
      "attack": -0.6700821052799488,
      "defense": -0.7082201906296757,
      "elo": 1154.6161948744825,
      "id": "british-virgin-islands",
      "name": "British Virgin Islands",
      "overall": -1.3783022959096245,
      "style": {}
    },
    {
      "attack": -0.7186835884021472,
      "defense": -0.8093003012781311,
      "elo": 1125.3642567306101,
      "id": "united-states-virgin-islands",
      "name": "United States Virgin Islands",
      "overall": -1.5279838896802782,
      "style": {}
    },
    {
      "attack": -0.7337963180859028,
      "defense": -0.8321210487826771,
      "elo": 1068.9490415045236,
      "id": "laos",
      "name": "Laos",
      "overall": -1.56591736686858,
      "style": {}
    },
    {
      "attack": -0.5862543512970113,
      "defense": -0.9861412891949469,
      "elo": 1302.6428032226215,
      "id": "saint-lucia",
      "name": "Saint Lucia",
      "overall": -1.5723956404919583,
      "style": {}
    },
    {
      "attack": -1.3055766484852875,
      "defense": -0.27956688515748485,
      "elo": 1139.9049008902016,
      "id": "somalia",
      "name": "Somalia",
      "overall": -1.5851435336427724,
      "style": {}
    },
    {
      "attack": -0.8571366752863486,
      "defense": -0.7423948905135656,
      "elo": 1247.0450948479202,
      "id": "gibraltar",
      "name": "Gibraltar",
      "overall": -1.5995315657999143,
      "style": {}
    },
    {
      "attack": -0.4970143248280332,
      "defense": -1.2060965738573286,
      "elo": 1126.6375582827584,
      "id": "guam",
      "name": "Guam",
      "overall": -1.7031108986853618,
      "style": {}
    },
    {
      "attack": -1.1810235628762882,
      "defense": -0.5468375717541286,
      "elo": 1268.6805372891095,
      "id": "afghanistan",
      "name": "Afghanistan",
      "overall": -1.727861134630417,
      "style": {}
    },
    {
      "attack": -0.8603140358786222,
      "defense": -0.9171254176235614,
      "elo": 1192.6893404717398,
      "id": "turks-and-caicos-islands",
      "name": "Turks and Caicos Islands",
      "overall": -1.7774394535021836,
      "style": {}
    },
    {
      "attack": -0.876756162220288,
      "defense": -0.9925515189940834,
      "elo": 1288.7299292164578,
      "id": "fr\u00f8ya",
      "name": "Fr\u00f8ya",
      "overall": -1.8693076812143714,
      "style": {}
    },
    {
      "attack": -1.5774385453863426,
      "defense": -0.3216817004791922,
      "elo": 1184.8406346383858,
      "id": "andorra",
      "name": "Andorra",
      "overall": -1.899120245865535,
      "style": {}
    },
    {
      "attack": -1.0619484344540537,
      "defense": -0.9041551779489333,
      "elo": 1176.5708750673364,
      "id": "cayman-islands",
      "name": "Cayman Islands",
      "overall": -1.966103612402987,
      "style": {}
    },
    {
      "attack": -1.2006258115792305,
      "defense": -0.8180674842640381,
      "elo": 1147.8741881412088,
      "id": "maldives",
      "name": "Maldives",
      "overall": -2.018693295843269,
      "style": {}
    },
    {
      "attack": -1.2813179050716819,
      "defense": -0.7592362187691374,
      "elo": 1254.4153723273166,
      "id": "antigua-and-barbuda",
      "name": "Antigua and Barbuda",
      "overall": -2.040554123840819,
      "style": {}
    },
    {
      "attack": -0.9439540232254932,
      "defense": -1.108919665419567,
      "elo": 1252.4921641044905,
      "id": "s\u00e3o-tom\u00e9-and-pr\u00edncipe",
      "name": "S\u00e3o Tom\u00e9 and Pr\u00edncipe",
      "overall": -2.05287368864506,
      "style": {}
    },
    {
      "attack": -1.0968986826156837,
      "defense": -0.9727120905621672,
      "elo": 1134.1967745830163,
      "id": "djibouti",
      "name": "Djibouti",
      "overall": -2.069610773177851,
      "style": {}
    },
    {
      "attack": -1.0293921727388287,
      "defense": -1.0433363354025686,
      "elo": 1039.5986463644927,
      "id": "timor-leste",
      "name": "Timor-Leste",
      "overall": -2.072728508141397,
      "style": {}
    },
    {
      "attack": -1.3218492378985058,
      "defense": -0.8368598256822,
      "elo": 1133.0576497211803,
      "id": "mongolia",
      "name": "Mongolia",
      "overall": -2.158709063580706,
      "style": {}
    },
    {
      "attack": -1.3222150636382497,
      "defense": -1.0974800864901666,
      "elo": 1039.6999505334884,
      "id": "brunei",
      "name": "Brunei",
      "overall": -2.4196951501284163,
      "style": {}
    },
    {
      "attack": -1.4429944546297284,
      "defense": -1.0600913467951987,
      "elo": 990.4224290012004,
      "id": "bhutan",
      "name": "Bhutan",
      "overall": -2.503085801424927,
      "style": {}
    },
    {
      "attack": -1.1571309230164972,
      "defense": -1.5092609583858598,
      "elo": 1142.3058088469604,
      "id": "bahamas",
      "name": "Bahamas",
      "overall": -2.6663918814023573,
      "style": {}
    },
    {
      "attack": -1.6532101022092847,
      "defense": -1.0189830840392418,
      "elo": 999.0248885447062,
      "id": "san-marino",
      "name": "San Marino",
      "overall": -2.6721931862485264,
      "style": {}
    },
    {
      "attack": -1.91234724976679,
      "defense": -0.8361530132161632,
      "elo": 1101.9624127630752,
      "id": "liechtenstein",
      "name": "Liechtenstein",
      "overall": -2.748500262982953,
      "style": {}
    },
    {
      "attack": -1.400023990294699,
      "defense": -1.4249971079426187,
      "elo": 1057.0374728359043,
      "id": "anguilla",
      "name": "Anguilla",
      "overall": -2.8250210982373174,
      "style": {}
    },
    {
      "attack": -1.63484068420588,
      "defense": -1.3016388708272477,
      "elo": 1119.8092668936283,
      "id": "seychelles",
      "name": "Seychelles",
      "overall": -2.9364795550331277,
      "style": {}
    },
    {
      "attack": -1.5222917170197516,
      "defense": -1.5073413659613166,
      "elo": 1013.3756794168432,
      "id": "macau",
      "name": "Macau",
      "overall": -3.0296330829810683,
      "style": {}
    },
    {
      "attack": -1.166933155226437,
      "defense": -2.1015586345524024,
      "elo": 1100.6977696418867,
      "id": "american-samoa",
      "name": "American Samoa",
      "overall": -3.2684917897788397,
      "style": {}
    }
  ]
}